{"cameraMode":{"drawMode":0,"name":"Shaded","section":"Shading Mode"},"sceneLighting":true,"audioPlay":false,"sceneViewState":{"showFog":true,"showMaterialUpdate":false,"showSkybox":true,"showFlares":true,"showImageEffects":true,"showParticleSystems":true},"in2DMode":false,"pivot":{"x":-218.55067443847657,"y":-176.4335479736328,"z":70.96311950683594},"rotation":{"x":0.26633089780807497,"y":-0.5441403985023499,"z":0.18766610324382783,"w":0.7733621001243591},"size":318.6260070800781,"orthographic":false}